{
    "access": "Members of the University",
    "address": "Raised Faculty Building\r\nSidgwick Avenue\r\nCambridge\r\nCB3 9DA",
    "atmosphere": [
        "relaxed",
        "modern",
        "social",
        "friendly"
    ],
    "building": "Casimir Lewy Library",
    "description": "",
    "disabled_access": true,
    "email_address": "philosophy@lib.cam.ac.uk",
    "facebook_url": "https://www.facebook.com/Lewylib",
    "facilities": [
        "daylight",
        "views",
        "free_wifi",
        "computers",
        "laptops_allowed",
        "signal",
        "printers_copiers",
        "refreshments",
        "break",
        "wheelchair_accessible",
        "blue_badge_parking",
        "accessible_toilets",
        "adjustable_furniture",
        "individual_study_space",
        "gender_neutral_toilets",
        "bike_racks",
        "smoking_area"
    ],
    "floor": "Second floor",
    "id": 20,
    "image": "/assets/photos/000-276-resized_philcomparea.jpg",
    "imagealt": "Philosophy - Computer Area",
    "lat": 52.20109,
    "lng": 0.10917,
    "location": "{\"type\":\"Point\",\"coordinates\":[0.10917,52.20109]}",
    "noise": "Background chatter",
    "opening_hours": {
        "friday": {
            "open": false,
            "from": "00:00",
            "to": "18:00"
        },
        "monday": {
            "open": false,
            "from": "00:00",
            "to": "18:00"
        },
        "saturday": {
            "open": false,
            "from": "10:00",
            "to": "17:00"
        },
        "sunday": {
            "open": false,
            "from": "00:00",
            "to": "24:00"
        },
        "thursday": {
            "open": false,
            "from": "00:00",
            "to": "18:00"
        },
        "tuesday": {
            "open": false,
            "from": "00:00",
            "to": "18:00"
        },
        "wednesday": {
            "open": false,
            "from": "00:00",
            "to": "18:00"
        }
    },
    "out_of_term_hours": {
        "friday": {
            "open": false,
            "from": "00:00",
            "to": "24:00"
        },
        "monday": {
            "open": false,
            "from": "00:00",
            "to": "24:00"
        },
        "saturday": {
            "open": false,
            "from": "00:00",
            "to": "24:00"
        },
        "sunday": {
            "open": false,
            "from": "00:00",
            "to": "24:00"
        },
        "thursday": {
            "open": false,
            "from": "00:00",
            "to": "24:00"
        },
        "tuesday": {
            "open": false,
            "from": "00:00",
            "to": "24:00"
        },
        "wednesday": {
            "open": false,
            "from": "00:00",
            "to": "24:00"
        }
    },
    "phone_number": "01223 762939",
    "phone_text": "Phone the space",
    "published": true,
    "restricted": false,
    "restriction": "",
    "slug": "philosophy-computer-area",
    "space_type": "Library space",
    "tags": [
        "light",
        "drop in",
        "Fetching service available"
    ],
    "title": "Philosophy - Computer Area",
    "term_time_hours": {
        "friday": {
            "open": false,
            "from": "00:00",
            "to": "18:00"
        },
        "monday": {
            "open": false,
            "from": "00:00",
            "to": "18:00"
        },
        "saturday": {
            "open": false,
            "from": "10:00",
            "to": "17:00"
        },
        "sunday": {
            "open": false,
            "from": "00:00",
            "to": "24:00"
        },
        "thursday": {
            "open": false,
            "from": "00:00",
            "to": "18:00"
        },
        "tuesday": {
            "open": false,
            "from": "00:00",
            "to": "18:00"
        },
        "wednesday": {
            "open": false,
            "from": "00:00",
            "to": "18:00"
        }
    },
    "twitter_screen_name": "lewylib",
    "url": "http://www.phil.cam.ac.uk/library",
    "url_text": "Visit the website",
    "work": [
        "close",
        "friends",
        "group",
        "in_a_library",
        "private"
    ]
}